pykey_gen.py
KeyGen_Python-0.0.2.dist-info/LICENSE
KeyGen_Python-0.0.2.dist-info/METADATA
KeyGen_Python-0.0.2.dist-info/WHEEL
KeyGen_Python-0.0.2.dist-info/top_level.txt
KeyGen_Python-0.0.2.dist-info/RECORD
